plumed
